pytsast/__init__.py
pytsast/cli.py
pytsast/factory.py
pytsast/core/__init__.py
pytsast/core/base.py
pytsast/core/serializer.py
pytsast/core/syntax_kind.py
pytsast/core/types.py
pytsast/nodes/__init__.py
pytsast/nodes/bindings.py
pytsast/nodes/class_elements.py
pytsast/nodes/common.py
pytsast/nodes/declarations.py
pytsast/nodes/expressions.py
pytsast/nodes/keywords.py
pytsast/nodes/literals.py
pytsast/nodes/misc.py
pytsast/nodes/modifiers.py
pytsast/nodes/object_elements.py
pytsast/nodes/statements.py
pytsast/nodes/tokens.py
pytsast/nodes/type_nodes.py
pytsast-0.1.6.dist-info/licenses/LICENSE
pytsast-0.1.6.dist-info/METADATA
pytsast-0.1.6.dist-info/WHEEL
pytsast-0.1.6.dist-info/top_level.txt
pytsast-0.1.6.dist-info/RECORD
