Metadata-Version: 2.4
Name: pytsast
Version: 0.1.6
Summary: Python TypeScript AST Generator - Create TypeScript code from Python
Author: jraylan
License: MIT
Requires-Python: >=3.11
License-File: LICENSE
Requires-Dist: pydantic>=2.0.0
Provides-Extra: dev
Requires-Dist: pytest>=7.0.0; extra == "dev"
Requires-Dist: pytest-cov>=4.0.0; extra == "dev"
Requires-Dist: mypy>=1.0.0; extra == "dev"
Dynamic: license-file
